CHANGELOG.txt
LICENSE.txt
README.txt
setup.cfg
setup.py
AuthKit.egg-info/PKG-INFO
AuthKit.egg-info/SOURCES.txt
AuthKit.egg-info/dependency_links.txt
AuthKit.egg-info/entry_points.txt
AuthKit.egg-info/not-zip-safe
AuthKit.egg-info/requires.txt
AuthKit.egg-info/top_level.txt
authkit/__init__.py
authkit/permissions.py
authkit/pylons_adaptors.py
authkit/authenticate/__init__.py
authkit/authenticate/basic.py
authkit/authenticate/cookie.py
authkit/authenticate/digest.py
authkit/authenticate/form.py
authkit/authenticate/forward.py
authkit/authenticate/multi.py
authkit/authenticate/open_id.py
authkit/authenticate/redirect.py
authkit/authenticate/sso/__init__.py
authkit/authenticate/sso/api.py
authkit/authenticate/sso/cas.py
authkit/authorize/__init__.py
authkit/authorize/pylons_adaptors.py
authkit/authorize/wsgi_adaptors.py
authkit/template/__init__.py
authkit/template/authenticate/setup.cfg
authkit/template/authenticate/setup.py_tmpl
authkit/template/authenticate/+package+/__init__.py_tmpl
authkit/template/authenticate/docs/license.txt_tmpl
authkit/template/authenticate/ez_setup/README.txt
authkit/template/authenticate/ez_setup/__init__.py
authkit/users/__init__.py
authkit/users/postgresql_driver.py
authkit/users/sqlalchemy_04_driver.py
authkit/users/sqlalchemy_driver/__init__.py
authkit/users/sqlalchemy_driver/sqlalchemy_03.py
authkit/users/sqlalchemy_driver/sqlalchemy_04.py
authkit/users/sqlalchemy_driver/sqlalchemy_044.py
docs/community.txt
docs/download.txt
docs/index.txt
docs/manual.txt
docs/pylons.txt
docs/pudge_template/class.html
docs/pudge_template/common.html
docs/pudge_template/document.html
docs/pudge_template/layout.css
docs/pudge_template/layout.html
docs/pudge_template/master-index.html
docs/pudge_template/member.html
docs/pudge_template/module-index.html
docs/pudge_template/module.html
docs/pudge_template/package-index.html
docs/pudge_template/pudge.css
docs/pudge_template/rst.css
docs/pudge_template/silvercity.css
docs/pudge_template/transitions.html
docs/scripts/shBrushCSharp.js
docs/scripts/shBrushCss.js
docs/scripts/shBrushDelphi.js
docs/scripts/shBrushJScript.js
docs/scripts/shBrushJava.js
docs/scripts/shBrushPasteIni.js
docs/scripts/shBrushPhp.js
