Metadata-Version: 1.0
Name: AuthKit
Version: 0.4.2
Summary: An authentication and authorization toolkit for WSGI applications and frameworks
Home-page: http://authkit.org/
Author: James Gardner
Author-email: james@pythonweb.org
License: MIT
Platform: UNKNOWN
